getIP/__init__.py
getIP/getIP.py
getip-1.0.15.dist-info/licenses/LICENSE
getip-1.0.15.dist-info/METADATA
getip-1.0.15.dist-info/WHEEL
getip-1.0.15.dist-info/top_level.txt
getip-1.0.15.dist-info/RECORD
