Metadata-Version: 2.4
Name: getIP
Version: 1.0.15
Summary: A small Package to allow you to get your Local IP
Author-email: AlphaO4 <AlphaO4@protonmail.com>
Project-URL: Homepage, https://github.com/alphaO4/getIP/
Project-URL: Issues, https://github.com/alphaO4/getIP/issues
Classifier: Programming Language :: Python :: 3
Classifier: License :: OSI Approved :: MIT License
Classifier: Operating System :: OS Independent
Requires-Python: >=3.6
License-File: LICENSE
Requires-Dist: requests
Dynamic: license-file
